MANIFEST.in
README.rst
setup.py
aliyunsdkcore/__init__.py
aliyunsdkcore/client.py
aliyunsdkcore/endpoints.xml
aliyunsdkcore/request.py
aliyunsdkcore/acs_exception/__init__.py
aliyunsdkcore/acs_exception/error_code.py
aliyunsdkcore/acs_exception/error_msg.py
aliyunsdkcore/acs_exception/error_type.py
aliyunsdkcore/acs_exception/exceptions.py
aliyunsdkcore/auth/__init__.py
aliyunsdkcore/auth/credentials.py
aliyunsdkcore/auth/algorithm/__init__.py
aliyunsdkcore/auth/algorithm/sha_hmac1.py
aliyunsdkcore/auth/algorithm/sha_hmac256.py
aliyunsdkcore/auth/composer/__init__.py
aliyunsdkcore/auth/composer/oss_signature_composer.py
aliyunsdkcore/auth/composer/roa_signature_composer.py
aliyunsdkcore/auth/composer/rpc_signature_composer.py
aliyunsdkcore/auth/signers/__init__.py
aliyunsdkcore/auth/signers/access_key_signer.py
aliyunsdkcore/auth/signers/ecs_ram_role_singer.py
aliyunsdkcore/auth/signers/ram_role_arn_signer.py
aliyunsdkcore/auth/signers/rsa_key_pair_signer.py
aliyunsdkcore/auth/signers/signer.py
aliyunsdkcore/auth/signers/signer_factory.py
aliyunsdkcore/auth/signers/sts_token_signer.py
aliyunsdkcore/auth/utils/__init__.py
aliyunsdkcore/auth/utils/md5_tool.py
aliyunsdkcore/auth/utils/url_encoder.py
aliyunsdkcore/http/__init__.py
aliyunsdkcore/http/format_type.py
aliyunsdkcore/http/http_request.py
aliyunsdkcore/http/http_response.py
aliyunsdkcore/http/method_type.py
aliyunsdkcore/http/protocol_type.py
aliyunsdkcore/profile/__init__.py
aliyunsdkcore/profile/location_service.py
aliyunsdkcore/profile/region_provider.py
aliyunsdkcore/profile/endpoint/__init__.py
aliyunsdkcore/profile/endpoint/endpoint_profile.py
aliyunsdkcore/profile/endpoint/endpoint_resolver.py
aliyunsdkcore/profile/endpoint/resolvers/__init__.py
aliyunsdkcore/profile/endpoint/resolvers/local_global_resolver.py
aliyunsdkcore/profile/endpoint/resolvers/local_regional_resolver.py
aliyunsdkcore/profile/endpoint/resolvers/location_service_resolver.py
dd_aliyun_python_sdk_core.egg-info/PKG-INFO
dd_aliyun_python_sdk_core.egg-info/SOURCES.txt
dd_aliyun_python_sdk_core.egg-info/dependency_links.txt
dd_aliyun_python_sdk_core.egg-info/requires.txt
dd_aliyun_python_sdk_core.egg-info/top_level.txt